[
  {
    "rate": "7.9",
    "cover_x": 580,
    "title": "漂亮女人",
    "url": "https://movie.douban.com/subject/1293825/",
    "playable": true,
    "cover": "https://img3.doubanio.com/view/photo/s_ratio_poster/public/p2199988222.jpg",
    "id": "1293825",
    "cover_y": 882,
    "is_new": false
  },
  {
    "rate": "7.8",
    "cover_x": 499,
    "title": "回魂夜",
    "url": "https://movie.douban.com/subject/1299765/",
    "playable": false,
    "cover": "https://img3.doubanio.com/view/photo/s_ratio_poster/public/p1020527660.jpg",
    "id": "1299765",
    "cover_y": 727,
    "is_new": false
  },
  {
    "rate": "7.5",
    "cover_x": 2362,
    "title": "人在囧途",
    "url": "https://movie.douban.com/subject/4237879/",
    "playable": true,
    "cover": "https://img1.doubanio.com/view/photo/s_ratio_poster/public/p500548437.jpg",
    "id": "4237879",
    "cover_y": 3543,
    "is_new": false
  },
  {
    "rate": "7.8",
    "cover_x": 2025,
    "title": "瑞士军刀男",
    "url": "https://movie.douban.com/subject/26437237/",
    "playable": true,
    "cover": "https://img3.doubanio.com/view/photo/s_ratio_poster/public/p2328680655.jpg",
    "id": "26437237",
    "cover_y": 3000,
    "is_new": false
  },
  {
    "rate": "8.1",
    "cover_x": 600,
    "title": "欢迎来到东莫村",
    "url": "https://movie.douban.com/subject/1433556/",
    "playable": false,
    "cover": "https://img1.doubanio.com/view/photo/s_ratio_poster/public/p1171939157.jpg",
    "id": "1433556",
    "cover_y": 860,
    "is_new": false
  },
  {
    "rate": "8.0",
    "cover_x": 1800,
    "title": "飞鹰艾迪",
    "url": "https://movie.douban.com/subject/3072064/",
    "playable": true,
    "cover": "https://img1.doubanio.com/view/photo/s_ratio_poster/public/p2322216899.jpg",
    "id": "3072064",
    "cover_y": 2571,
    "is_new": false
  },
  {
    "rate": "8.5",
    "cover_x": 1000,
    "title": "午夜狂奔",
    "url": "https://movie.douban.com/subject/1294699/",
    "playable": true,
    "cover": "https://img3.doubanio.com/view/photo/s_ratio_poster/public/p1483943303.jpg",
    "id": "1294699",
    "cover_y": 1500,
    "is_new": false
  },
  {
    "rate": "8.1",
    "cover_x": 1000,
    "title": "如月疑云",
    "url": "https://movie.douban.com/subject/2361826/",
    "playable": false,
    "cover": "https://img3.doubanio.com/view/photo/s_ratio_poster/public/p655393674.jpg",
    "id": "2361826",
    "cover_y": 1414,
    "is_new": false
  },
  {
    "rate": "7.8",
    "cover_x": 420,
    "title": "斗牛",
    "url": "https://movie.douban.com/subject/4009651/",
    "playable": true,
    "cover": "https://img3.doubanio.com/view/photo/s_ratio_poster/public/p2128617874.jpg",
    "id": "4009651",
    "cover_y": 600,
    "is_new": false
  },
  {
    "rate": "8.5",
    "cover_x": 1012,
    "title": "南方公园",
    "url": "https://movie.douban.com/subject/1295428/",
    "playable": true,
    "cover": "https://img3.doubanio.com/view/photo/s_ratio_poster/public/p1852116626.jpg",
    "id": "1295428",
    "cover_y": 1500,
    "is_new": false
  },
  {
    "rate": "8.0",
    "cover_x": 3375,
    "title": "追捕野蛮人",
    "url": "https://movie.douban.com/subject/26411201/",
    "playable": true,
    "cover": "https://img3.doubanio.com/view/photo/s_ratio_poster/public/p2371503931.jpg",
    "id": "26411201",
    "cover_y": 5000,
    "is_new": false
  },
  {
    "rate": "7.9",
    "cover_x": 764,
    "title": "超新约全书",
    "url": "https://movie.douban.com/subject/25958704/",
    "playable": true,
    "cover": "https://img3.doubanio.com/view/photo/s_ratio_poster/public/p2240337400.jpg",
    "id": "25958704",
    "cover_y": 1024,
    "is_new": false
  },
  {
    "rate": "8.3",
    "cover_x": 1421,
    "title": "魔幻时刻",
    "url": "https://movie.douban.com/subject/2157507/",
    "playable": false,
    "cover": "https://img3.doubanio.com/view/photo/s_ratio_poster/public/p637438422.jpg",
    "id": "2157507",
    "cover_y": 2000,
    "is_new": false
  },
  {
    "rate": "8.0",
    "cover_x": 500,
    "title": "金玉满堂",
    "url": "https://movie.douban.com/subject/1295374/",
    "playable": false,
    "cover": "https://img3.doubanio.com/view/photo/s_ratio_poster/public/p950775183.jpg",
    "id": "1295374",
    "cover_y": 695,
    "is_new": false
  },
  {
    "rate": "8.1",
    "cover_x": 2025,
    "title": "葬礼上的死亡",
    "url": "https://movie.douban.com/subject/2003389/",
    "playable": false,
    "cover": "https://img1.doubanio.com/view/photo/s_ratio_poster/public/p501057857.jpg",
    "id": "2003389",
    "cover_y": 3000,
    "is_new": false
  },
  {
    "rate": "7.8",
    "cover_x": 464,
    "title": "旋风小子",
    "url": "https://movie.douban.com/subject/1408312/",
    "playable": true,
    "cover": "https://img1.doubanio.com/view/photo/s_ratio_poster/public/p2352121968.jpg",
    "id": "1408312",
    "cover_y": 675,
    "is_new": false
  },
  {
    "rate": "7.7",
    "cover_x": 413,
    "title": "大腕",
    "url": "https://movie.douban.com/subject/1304022/",
    "playable": true,
    "cover": "https://img3.doubanio.com/view/photo/s_ratio_poster/public/p1232528944.jpg",
    "id": "1304022",
    "cover_y": 560,
    "is_new": false
  },
  {
    "rate": "8.7",
    "cover_x": 450,
    "title": "纸月亮",
    "url": "https://movie.douban.com/subject/1303357/",
    "playable": true,
    "cover": "https://img3.doubanio.com/view/photo/s_ratio_poster/public/p1056421242.jpg",
    "id": "1303357",
    "cover_y": 620,
    "is_new": false
  },
  {
    "rate": "8.6",
    "cover_x": 600,
    "title": "音乐会",
    "url": "https://movie.douban.com/subject/3285642/",
    "playable": false,
    "cover": "https://img3.doubanio.com/view/photo/s_ratio_poster/public/p767824526.jpg",
    "id": "3285642",
    "cover_y": 858,
    "is_new": false
  },
  {
    "rate": "8.7",
    "cover_x": 800,
    "title": "街角的商店",
    "url": "https://movie.douban.com/subject/1299166/",
    "playable": false,
    "cover": "https://img1.doubanio.com/view/photo/s_ratio_poster/public/p1362848748.jpg",
    "id": "1299166",
    "cover_y": 1113,
    "is_new": false
  }
]